pynani/Messenger.py
pynani/__init__.py
pynani/utils/__init__.py
pynani/utils/buttons.py
pynani/utils/logs.py
pynani/utils/quick_reply.py
pynani/utils/receipt.py
pynani-1.4.0.dist-info/LICENSE
pynani-1.4.0.dist-info/METADATA
pynani-1.4.0.dist-info/WHEEL
pynani-1.4.0.dist-info/top_level.txt
pynani-1.4.0.dist-info/RECORD
