Metadata-Version: 2.1
Name: pynani
Version: 1.4.0
Summary: A package to wrap the Messenger API
Author-email: Jorge Juarez <jorgeang33@gmail.com>
License: MIT License
Project-URL: Bug Tracker, https://github.com/jorge-jrzz/Pynani/issues
Project-URL: Repository, https://github.com/jorge-jrzz/Pynani
Keywords: Messenger,wrapper,Meta,API,Facebook,Pynani,PyMessenger
Classifier: Intended Audience :: Developers
Classifier: Intended Audience :: Customer Service
Classifier: Topic :: Software Development :: Build Tools
Classifier: Topic :: Communications :: Chat
Classifier: Topic :: Software Development :: Libraries :: Python Modules
Classifier: Topic :: Software Development :: Version Control :: Git
Classifier: Topic :: Utilities
Classifier: Topic :: Documentation :: Sphinx
Classifier: License :: OSI Approved :: MIT License
Classifier: Programming Language :: Python :: 3
Classifier: Programming Language :: Python :: 3.10
Classifier: Programming Language :: Python :: 3.11
Classifier: Programming Language :: Python :: 3.12
Classifier: Programming Language :: Python :: 3.13
Classifier: Programming Language :: Python :: 3.14
Requires-Python: >=3.10
License-File: LICENSE
Requires-Dist: requests>=2.32.3
Requires-Dist: colorlog>=6.8.2
